ec2_manager/__init__.py
ec2_manager/__main__.py
ec2_manager/cli.py
ec2_manager/template/.dockerignore
ec2_manager/template/.gitignore
ec2_manager/template/config.yaml
ec2_manager/template/override.py
ec2_manager/template/.github/workflows/deploy.yaml
ec2_manager/template/compose/docker-compose.yaml
ec2_manager/template/terraform/data.tf
ec2_manager/template/terraform/outputs.tf
ec2_manager/template/terraform/permissions.tf
ec2_manager/template/terraform/provider.tf
ec2_manager/template/terraform/resources.tf
ec2_manager/template/terraform/user_data_amzn2_arm64.sh.tpl
ec2_manager/template/terraform/user_data_amzn2_x86_64.sh.tpl
ec2_manager/template/terraform/user_data_ubuntu_x86_64.sh.tpl
ec2_manager/template/terraform/variables.tf
ec2_manager-0.0.61.dist-info/METADATA
ec2_manager-0.0.61.dist-info/WHEEL
ec2_manager-0.0.61.dist-info/entry_points.txt
ec2_manager-0.0.61.dist-info/top_level.txt
ec2_manager-0.0.61.dist-info/RECORD
