Metadata-Version: 2.1
Name: ec2-manager
Version: 0.0.61
Home-page: https://github.com/jamesbaber1/ec2-manager
Author: jamesbaber1
Author-email: 
Project-URL: Bug Tracker, https://github.com/jamesbaber1/ec2-manager/issues
Classifier: Programming Language :: Python :: 3
Classifier: License :: OSI Approved :: MIT License
Classifier: Operating System :: OS Independent
Requires-Dist: pytz >=2022.2.1
Requires-Dist: PyYAML >=6.0
Requires-Dist: PyGithub >=1.58.1
Requires-Dist: boto3 >=1.24.56
Requires-Dist: click >=8.0.3
Requires-Dist: pyperclip >=1.8.2
Requires-Dist: python-dotenv >=0.19.2
